README.rst
_description.org
lh-agpl3-LICENSE.txt
pyproject.toml
setup.py
bin/notqmailMua-sysd.cs
bin/qmail-assemble.cs
bin/qmail-binsPrep.cs
bin/qmail-inject-bisos.cs
bin/qmail-remote-bisos.cs
bin/qmailAdmin.cs
bin/qmailConfig.cs
bin/qmailControl.cs
bisos/__init__.py
bisos.qmail.egg-info/PKG-INFO
bisos.qmail.egg-info/SOURCES.txt
bisos.qmail.egg-info/dependency_links.txt
bisos.qmail.egg-info/not-zip-safe
bisos.qmail.egg-info/requires.txt
bisos.qmail.egg-info/top_level.txt
bisos/qmail/__init__.py
bisos/qmail/notqmailSysd.py
bisos/qmail/qmail.py
bisos/qmail/qmailAdmin.py
bisos/qmail/qmailControl.py
bisos/qmail/qmailInjectWrapper.py
bisos/qmail/qmailRemoteWrapper.py
bisos/qmail/qmail_binsPrep.py
bisos/qmail/qmail_csu.py